[
  {
    "id": 1,
    "category": "한식",
    "name": "wecode1",
    "rates": 1000,
    "reviews": "1000개",
    "img": "https://t1.kakaocdn.net/friends/prod/main_tab/home/home_20201103134054_kr.jpg?type=thumb&opt=R329x247@2xa"
  },
  {
    "id": 2,
    "category": "한식",
    "name": "wecode2",
    "rates": 150,
    "reviews": "2000개",
    "img": "https://t1.kakaocdn.net/friends/prod/main_tab/home/home_20201106164745_kr.jpg?type=thumb&opt=R329x247@2xa"
  },
  {
    "id": 3,
    "category": "한식",
    "name": "wecode3",
    "rates": 200,
    "reviews": "3000개",
    "img": "https://t1.daumcdn.net/friends/prod/product/20201020152815054_8809721505908_AW_00.jpg?type=thumb&opt=R103x103@2xa",
    "address": "위코드시 위해요 3동",
    "telephone": "000-000-0000"
  },
  {
    "id": 4,
    "category": "중식",
    "name": "wecode4",
    "rates": 25,
    "reviews": "4000개",
    "img": "https://t1.daumcdn.net/friends/prod/product/20201020152905998_8809721505922_AW_00.jpg?type=thumb&opt=R103x103@2xa"
  },
  {
    "id": 5,
    "Category": "중식",
    "name": "wecode5",
    "rates": 30,
    "reviews": "5000개",
    "img": "https://t1.kakaocdn.net/friends/prod/main_tab/home/home_20201111183631_kr.jpg?type=thumb&opt=R335x187@2xa",
    "address": "위코드시 위해요 5동",
    "telephone": "000-000-0000"
  },
  {
    "id": 6,
    "category": "일식",
    "name": "wecode6",
    "rates": 40,
    "reviews": "45000개",
    "img": "https://t1.kakaocdn.net/friends/prod/main_tab/home/home_20201111183631_kr.jpg?type=thumb&opt=R335x187@2xa"
  },
  {
    "id": 7,
    "category": "일식",
    "name": "wecode7",
    "rates": 500,
    "reviews": "200개",
    "img": "https://t1.kakaocdn.net/friends/prod/main_tab/home/home_20201111183631_kr.jpg?type=thumb&opt=R335x187@2xa"
  },
  {
    "id": 8,
    "category": "일식",
    "name": "wecode8",
    "rates": 60,
    "reviews": "500개",
    "img": "https://t1.kakaocdn.net/friends/prod/main_tab/home/home_20201111183631_kr.jpg?type=thumb&opt=R335x187@2xa"
  },
  {
    "id": 9,
    "category": "중식",
    "name": "wecode9",
    "rates": 70,
    "reviews": "510개",
    "img": "https://t1.kakaocdn.net/friends/prod/main_tab/home/home_20201111183631_kr.jpg?type=thumb&opt=R335x187@2xa"
  },
  {
    "id": 10,
    "category": "한식",
    "name": "wecode10",
    "rates": 80,
    "reviews": "10개",
    "img": "https://t1.kakaocdn.net/friends/prod/main_tab/home/home_20201111183631_kr.jpg?type=thumb&opt=R335x187@2xa"
  }
]
